digioFunction/__init__.py
digioFunction/__version__.py
digioFunction/digioFunc.py
digioFunction/entry_points.py
villa_digiofunction_pinpinteamakorn-0.0.7.dist-info/LICENSE
villa_digiofunction_pinpinteamakorn-0.0.7.dist-info/METADATA
villa_digiofunction_pinpinteamakorn-0.0.7.dist-info/WHEEL
villa_digiofunction_pinpinteamakorn-0.0.7.dist-info/entry_points.txt
villa_digiofunction_pinpinteamakorn-0.0.7.dist-info/top_level.txt
villa_digiofunction_pinpinteamakorn-0.0.7.dist-info/RECORD
