Metadata-Version: 2.1
Name: villa-digiofunction-pinpinteamakorn
Version: 0.0.7
Summary: interface for digio adapter
Home-page: https://github.com/thanakijwanavit/villaWallet
Author: Pin Pin Tea-makorn
Author-email: teamakorn@pinnaree.com
License: Apache 2.0
Keywords: villa digio function
Platform: UNKNOWN
Classifier: Development Status :: 4 - Beta
Classifier: Intended Audience :: Developers
Classifier: Programming Language :: Python :: 3.8
Requires-Python: >=3.6.*
Requires-Dist: requests
Requires-Dist: boto3
Requires-Dist: villa-digioadapter-jirawutchayapong
